authomatic/__init__.py
authomatic/adapters.py
authomatic/core.py
authomatic/exceptions.py
authomatic/six.py
authomatic/extras/__init__.py
authomatic/extras/flask.py
authomatic/extras/interfaces.py
authomatic/extras/gae/__init__.py
authomatic/extras/gae/openid.py
authomatic/providers/__init__.py
authomatic/providers/gaeopenid.py
authomatic/providers/oauth1.py
authomatic/providers/oauth2.py
authomatic/providers/openid.py
authomatic/providers/persona.py
tests/__init__.py
tests/conftest.py
tests/functional_tests/__init__.py
tests/functional_tests/config_public.py
tests/functional_tests/config_secret.py
tests/functional_tests/constants.py
tests/functional_tests/test_providers.py
tests/functional_tests/expected_values/__init__.py
tests/functional_tests/expected_values/amazon.py
tests/functional_tests/expected_values/bitbucket.py
tests/functional_tests/expected_values/bitly.py
tests/functional_tests/expected_values/deviantart.py
tests/functional_tests/expected_values/eventbrite.py
tests/functional_tests/expected_values/facebook.py
tests/functional_tests/expected_values/flickr.py
tests/functional_tests/expected_values/foursquare.py
tests/functional_tests/expected_values/github.py
tests/functional_tests/expected_values/google.py
tests/functional_tests/expected_values/linkedin.py
tests/functional_tests/expected_values/meetup.py
tests/functional_tests/expected_values/openid_livejournal.py
tests/functional_tests/expected_values/openid_verisignlabs.py
tests/functional_tests/expected_values/openid_wordpress.py
tests/functional_tests/expected_values/openid_yahoo.py
tests/functional_tests/expected_values/paypal.py
tests/functional_tests/expected_values/plurk.py
tests/functional_tests/expected_values/reddit.py
tests/functional_tests/expected_values/tumblr.py
tests/functional_tests/expected_values/twitter.py
tests/functional_tests/expected_values/vimeo.py
tests/functional_tests/expected_values/vk.py
tests/functional_tests/expected_values/windowslive.py
Authomatic-1.3.0.dist-info/LICENSE.txt
Authomatic-1.3.0.dist-info/METADATA
Authomatic-1.3.0.dist-info/WHEEL
Authomatic-1.3.0.dist-info/top_level.txt
Authomatic-1.3.0.dist-info/RECORD
